AUTHORS
CHANGES.rst
MANIFEST.in
README.rst
setup.py
django_output_validator.egg-info/PKG-INFO
django_output_validator.egg-info/SOURCES.txt
django_output_validator.egg-info/dependency_links.txt
django_output_validator.egg-info/top_level.txt
output_validator/__init__.py
output_validator/middleware.py
output_validator/models.py
output_validator/urls.py
output_validator/views.py
output_validator/migrations/0001_initial.py
output_validator/migrations/__init__.py
output_validator/templates/output_validator/base.html
output_validator/templates/output_validator/validationfailure_detail.html
output_validator/templates/output_validator/validationfailure_list.html
output_validator/templatetags/__init__.py
output_validator/templatetags/output_validator.py