Metadata-Version: 1.0
Name: django-output-validator
Version: 1.5
Summary: App to catch HTML errors (or other errors) in outgoing Django pages.
Home-page: http://lukeplant.me.uk/resources/djangovalidator/
Author: Luke Plant
Author-email: L.Plant.98@cantab.net
License: MIT
Keywords: django HTML XHTML validation validator
Platform: UNKNOWN
Classifier: Development Status :: 5 - Production/Stable
Classifier: Environment :: Web Environment
Classifier: Intended Audience :: Developers
Classifier: License :: OSI Approved :: MIT License
Classifier: Operating System :: OS Independent
Classifier: Programming Language :: Python
Classifier: Framework :: Django
Classifier: Topic :: Internet :: WWW/HTTP :: Dynamic Content :: CGI Tools/Libraries
Classifier: Topic :: Software Development :: Testing
